.gitignore
.gitignore-github
LICENSE
MANIFEST.in
Makefile
README.md
README.rst
benchmark.py
build.py
setup.py
tox.ini
highwayhash/__init__.py
highwayhash_cffi.egg-info/PKG-INFO
highwayhash_cffi.egg-info/SOURCES.txt
highwayhash_cffi.egg-info/dependency_links.txt
highwayhash_cffi.egg-info/requires.txt
highwayhash_cffi.egg-info/top_level.txt
sources/LICENSE
sources/highwayhash.c
sources/highwayhash.h
tests/conftest.py
tests/test_cases.py
tests/test_functionality.py
tests/test_validation.py