Metadata-Version: 1.1
Name: highwayhash-cffi
Version: 0.1.6
Summary: Tested, performant HighwayHash bindings for Python 3 with support for all output lengths.
Home-page: https://github.com/kpdemetriou/highwayhash-cffi
Author: Phil Demetriou
Author-email: inbox@philonas.net
License: BSD
Platform: UNKNOWN
Classifier: Development Status :: 4 - Beta
Classifier: Intended Audience :: Developers
Classifier: Intended Audience :: Science/Research
Classifier: Intended Audience :: System Administrators
Classifier: Intended Audience :: Telecommunications Industry
Classifier: License :: OSI Approved :: BSD License
Classifier: Programming Language :: C
Classifier: Programming Language :: Python :: 3
Classifier: Programming Language :: Python :: 3 :: Only
Classifier: Topic :: Security
Classifier: Topic :: Security :: Cryptography
Classifier: Topic :: Utilities
